<items>
  <item id="0">
    <top> 1 </top>
    <bottom> 1 </bottom>
    <left> 1 </left>
    <right> 1 </right>
  </item>
  <item id="1">
    <top> 0 1 2 </top>
    <bottom> 0 1 2 </bottom>
    <left> 0 1 2 </left>
    <right> 0 1 2 </right>
  </item>
  <item id="2">
    <top> 1 2 3 </top>
    <bottom> 1 2 3 </bottom>
    <left> 1 2 3 </left>
    <right> 1 2 3 </right>
  </item>
  <item id="3">
    <top> 2 3 4 </top>
    <bottom> 2 3 4 </bottom>
    <left> 2 3 4 </left>
    <right> 2 3 4 </right>
  </item>
  <item id="4">
    <top> 3 4 5 </top>
    <bottom> 3 4 5 </bottom>
    <left> 3 4 5 </left>
    <right> 3 4 5 </right>
  </item>
  <item id="5">
    <top> 4 5 6 </top>
    <bottom> 4 5 6 </bottom>
    <left> 4 5 6 </left>
    <right> 4 5 6 </right>
  </item>
  <item id="6">
    <top> 5 6 7 </top>
    <bottom> 5 6 7 </bottom>
    <left> 5 6 7 </left>
    <right> 5 6 7 </right>
  </item>
  <item id="7">
    <top> 6 7 8 </top>
    <bottom> 6 7 8 </bottom>
    <left> 6 7 8 </left>
    <right> 6 7 8 </right>
  </item>
  <item id="8">
    <top> 7 </top>
    <bottom> 7 </bottom>
    <left> 7 </left>
    <right> 7 </right>
  </item>
</items>